{
  
    
        "post0": {
            "title": "Minha página",
            "content": "import pandas as pd import numpy as np . data = np.random.randint(0,1000,(10,10)) data . array([[ 56, 755, 467, 654, 48, 776, 813, 312, 236, 967], [216, 146, 618, 576, 997, 593, 726, 396, 990, 182], [378, 501, 575, 358, 436, 986, 131, 793, 638, 130], [168, 589, 853, 338, 620, 833, 387, 162, 837, 188], [147, 963, 850, 883, 158, 507, 534, 31, 32, 449], [840, 8, 961, 475, 629, 1, 411, 972, 214, 783], [ 63, 185, 204, 515, 662, 572, 754, 954, 645, 822], [219, 269, 659, 140, 374, 139, 484, 509, 222, 970], [497, 814, 722, 716, 966, 615, 27, 953, 60, 992], [850, 795, 261, 627, 132, 174, 988, 679, 46, 949]]) . df1 = pd.DataFrame(data) df1 . 0 1 2 3 4 5 6 7 8 9 . 0 56 | 755 | 467 | 654 | 48 | 776 | 813 | 312 | 236 | 967 | . 1 216 | 146 | 618 | 576 | 997 | 593 | 726 | 396 | 990 | 182 | . 2 378 | 501 | 575 | 358 | 436 | 986 | 131 | 793 | 638 | 130 | . 3 168 | 589 | 853 | 338 | 620 | 833 | 387 | 162 | 837 | 188 | . 4 147 | 963 | 850 | 883 | 158 | 507 | 534 | 31 | 32 | 449 | . 5 840 | 8 | 961 | 475 | 629 | 1 | 411 | 972 | 214 | 783 | . 6 63 | 185 | 204 | 515 | 662 | 572 | 754 | 954 | 645 | 822 | . 7 219 | 269 | 659 | 140 | 374 | 139 | 484 | 509 | 222 | 970 | . 8 497 | 814 | 722 | 716 | 966 | 615 | 27 | 953 | 60 | 992 | . 9 850 | 795 | 261 | 627 | 132 | 174 | 988 | 679 | 46 | 949 | . df2 = pd.DataFrame(data) df2 . 0 1 2 3 4 5 6 7 8 9 . 0 56 | 755 | 467 | 654 | 48 | 776 | 813 | 312 | 236 | 967 | . 1 216 | 146 | 618 | 576 | 997 | 593 | 726 | 396 | 990 | 182 | . 2 378 | 501 | 575 | 358 | 436 | 986 | 131 | 793 | 638 | 130 | . 3 168 | 589 | 853 | 338 | 620 | 833 | 387 | 162 | 837 | 188 | . 4 147 | 963 | 850 | 883 | 158 | 507 | 534 | 31 | 32 | 449 | . 5 840 | 8 | 961 | 475 | 629 | 1 | 411 | 972 | 214 | 783 | . 6 63 | 185 | 204 | 515 | 662 | 572 | 754 | 954 | 645 | 822 | . 7 219 | 269 | 659 | 140 | 374 | 139 | 484 | 509 | 222 | 970 | . 8 497 | 814 | 722 | 716 | 966 | 615 | 27 | 953 | 60 | 992 | . 9 850 | 795 | 261 | 627 | 132 | 174 | 988 | 679 | 46 | 949 | . df3 = pd.DataFrame(data) df3 . 0 1 2 3 4 5 6 7 8 9 . 0 56 | 755 | 467 | 654 | 48 | 776 | 813 | 312 | 236 | 967 | . 1 216 | 146 | 618 | 576 | 997 | 593 | 726 | 396 | 990 | 182 | . 2 378 | 501 | 575 | 358 | 436 | 986 | 131 | 793 | 638 | 130 | . 3 168 | 589 | 853 | 338 | 620 | 833 | 387 | 162 | 837 | 188 | . 4 147 | 963 | 850 | 883 | 158 | 507 | 534 | 31 | 32 | 449 | . 5 840 | 8 | 961 | 475 | 629 | 1 | 411 | 972 | 214 | 783 | . 6 63 | 185 | 204 | 515 | 662 | 572 | 754 | 954 | 645 | 822 | . 7 219 | 269 | 659 | 140 | 374 | 139 | 484 | 509 | 222 | 970 | . 8 497 | 814 | 722 | 716 | 966 | 615 | 27 | 953 | 60 | 992 | . 9 850 | 795 | 261 | 627 | 132 | 174 | 988 | 679 | 46 | 949 | .",
            "url": "https://brunozoli.github.io/my_first_blog/blog/2021/02/17/Primeiro-post.html",
            "relUrl": "/blog/2021/02/17/Primeiro-post.html",
            "date": " • Feb 17, 2021"
        }
        
    
  

  
  

  
      ,"page1": {
          "title": "About Me",
          "content": "This website is powered by fastpages 1. . a blogging platform that natively supports Jupyter notebooks in addition to other formats. &#8617; . |",
          "url": "https://brunozoli.github.io/my_first_blog/about/",
          "relUrl": "/about/",
          "date": ""
      }
      
  

  

  
  

  

  
  

  

  
  

  
  

  
  

  
      ,"page10": {
          "title": "",
          "content": "Sitemap: {{ “sitemap.xml” | absolute_url }} | .",
          "url": "https://brunozoli.github.io/my_first_blog/robots.txt",
          "relUrl": "/robots.txt",
          "date": ""
      }
      
  

}